genlang/__init__.py
genlang/cli.py
genlang/core.py
genlang-0.0.2.dist-info/licenses/LICENSE
genlang-0.0.2.dist-info/METADATA
genlang-0.0.2.dist-info/WHEEL
genlang-0.0.2.dist-info/entry_points.txt
genlang-0.0.2.dist-info/top_level.txt
genlang-0.0.2.dist-info/RECORD
