Metadata-Version: 2.4
Name: genlang
Version: 0.0.2
Summary: Genlang — ultra-strict symbolic/reactive dynamic language
Author-email: Ege Güvener <egeguvener0808@gmail.com>
License: MIT
Project-URL: Homepage, https://github.com/egegvner/Genlang
Project-URL: Source, https://github.com/egegvner/Genlang
Classifier: Programming Language :: Python :: 3
Classifier: License :: OSI Approved :: MIT License
Classifier: Operating System :: OS Independent
Requires-Python: >=3.8
License-File: LICENSE
Dynamic: license-file
